django_zoom_meetings/__init__.py
django_zoom_meetings-0.1.0.dist-info/LICENCE.txt
django_zoom_meetings-0.1.0.dist-info/METADATA
django_zoom_meetings-0.1.0.dist-info/WHEEL
django_zoom_meetings-0.1.0.dist-info/top_level.txt
django_zoom_meetings-0.1.0.dist-info/RECORD
