Metadata-Version: 1.1
Name: django_zoom_meetings
Version: 0.1.0
Summary: Python package for creating and deleting zoom meetings
Home-page: https://github.com/JoeyAlpha5/django-zoom-meetings
Author: Jalome Chirwa
Author-email: chjalome@gmail.com
License: UNKNOWN
Keywords: python,django,zoom
Platform: UNKNOWN
Classifier: Development Status :: 3 - Alpha
Classifier: Intended Audience :: Education
Classifier: Programming Language :: Python :: 2
Classifier: Programming Language :: Python :: 3
Classifier: Operating System :: MacOS :: MacOS X
Classifier: Operating System :: Microsoft :: Windows
